folderpodgen.py
folderpodgen-0.2.dist-info/METADATA
folderpodgen-0.2.dist-info/RECORD
folderpodgen-0.2.dist-info/WHEEL
folderpodgen-0.2.dist-info/entry_points.txt
folderpodgen-0.2.dist-info/top_level.txt
