Metadata-Version: 2.1
Name: folderpodgen
Version: 0.2
Summary: Make a podcast RSS from a folder of MP3 files
Home-page: https://github.com/lgaggini/drowse
Author: UNKNOWN
Author-email: lg@lgaggini.net
License: LICENSE
Keywords: PODCAST,MP3,RSS
Platform: UNKNOWN
Classifier: Programming Language :: Python
Classifier: Development Status :: 4 - Beta
Classifier: Environment :: Console
Classifier: Intended Audience :: End Users/Desktop
Classifier: License :: OSI Approved :: GNU General Public License v3 (GPLv3)
Classifier: Operating System :: OS Independent
Classifier: Topic :: Multimedia :: Sound/Audio
Requires-Dist: click
Requires-Dist: podgen
Requires-Dist: mutagen
